bls_api/__init__.py
bls_api/labor_series.json
bls_api/main.py
bls_api/protocols.py
bls_api-0.1.4.dist-info/LICENSE
bls_api-0.1.4.dist-info/METADATA
bls_api-0.1.4.dist-info/WHEEL
bls_api-0.1.4.dist-info/top_level.txt
bls_api-0.1.4.dist-info/RECORD
