Metadata-Version: 2.1
Name: bls-api
Version: 0.1.4
Summary: 'This package allows to get data from Bureau of Labor Statistics'
Home-page: https://github.com/tiennguyennesbook/bls_api
Author: Tien Nguyen
Author-email: tien.nguyen@nesbook.io
Classifier: Development Status :: 5 - Production/Stable
Classifier: License :: OSI Approved :: MIT License
Classifier: Intended Audience :: Developers
Classifier: Programming Language :: Python :: 3
Classifier: Operating System :: OS Independent
License-File: LICENSE
